{"P001": {"name": "Mannnn", "city": "string", "age": 1, "gender": "Male", "height": 1.0, "weight": 1.0, "bmi": 1.0, "verdict": "Underweight"}, "P002": {"name": "Mannnn", "city": "string", "age": 1, "gender": "Male", "height": 4.0, "weight": 70.0, "bmi": 4.38, "verdict": "Underweight"}, "P005": {"name": "Karan", "weight": 70, "age": 19, "height": 18.4, "caste": "Hindu", "gender": "Female", "issue": "Headache", "bmi": 42}, "P006": {"name": "leo", "city": "hyderabad", "age": 15, "gender": "Male", "height": 6.0, "weight": 14.9, "bmi": 0.41, "verdict": "Underweight"}, "P007": {"name": "Hello", "city": "Agartala", "age": 16, "gender": "Male", "height": 4.9, "weight": 47.0, "bmi": 1.96, "verdict": "Underweight"}, "P008": {"name": "Hii_my_name", "city": "Jirania", "age": 19, "gender": "Female", "height": 4.3, "weight": 62.0, "bmi": 3.35, "verdict": "Underweight"}, "P009": {"name": "leo", "city": "fd", "age": 1, "gender": "Male", "height": 1.0, "weight": 1.0, "bmi": 1.0, "verdict": "Underweight"}, "P010": {"name": "leo", "city": "hyderabad", "age": 15, "gender": "Male", "height": 6.0, "weight": 14.9, "bmi": 0.41, "verdict": "Underweight"}, "P011": {"name": "Kis mis", "city": "agartala", "age": 22, "gender": "Male", "height": 5.3, "weight": 62.0, "bmi": 2.21, "verdict": "Underweight"}, "P012": {"name": "Shabu kola batasha", "city": "agartala", "age": 22, "gender": "Male", "height": 5.3, "weight": 62.0, "bmi": 2.21, "verdict": "Underweight"}}